cheltuieli_desktop/__init__.py
cheltuieli_desktop/control.py
cheltuieli_desktop/gui_desktop.py
cheltuieli_desktop-0.0.1.dist-info/METADATA
cheltuieli_desktop-0.0.1.dist-info/WHEEL
cheltuieli_desktop-0.0.1.dist-info/top_level.txt
cheltuieli_desktop-0.0.1.dist-info/RECORD
