Metadata-Version: 2.1
Name: cheltuieli-desktop
Version: 0.0.1
Summary: desktop_version_cheltuieli
Home-page: https://github.com/pypa/sampleproject
Author: Radu M.
Author-email: radu.mircea@yahoo.com
Project-URL: Bug Tracker, https://github.com/pypa/sampleproject/issues
Classifier: Programming Language :: Python :: 3
Classifier: License :: OSI Approved :: MIT License
Classifier: Operating System :: OS Independent
Requires-Python: >=3.6
Requires-Dist: mysqlquerys
